README.md
setup.py
cursofiap/__init__.py
cursofiap/core.py
projeto_fiap.egg-info/PKG-INFO
projeto_fiap.egg-info/SOURCES.txt
projeto_fiap.egg-info/dependency_links.txt
projeto_fiap.egg-info/top_level.txt