Metadata-Version: 2.1
Name: projeto-fiap
Version: 1.0.0
Summary: Descricao da sua lib cursofiap
Home-page: https://github.com/m-novelli/projeto_fiap
Author: Marina N M
Author-email: mah.novelli@hotmail.com
License: MIT
